quizzing/__init__.py
quizzing/do_quiz/__init__.py
quizzing/do_quiz/quiz_session.py
quizzing/do_quiz/quiz_timer.py
quizzing/question_bank/__init__.py
quizzing/question_bank/question_loader.py
quizzing/question_bank/question_manager.py
quizzing-0.0.1.dist-info/LICENSE.txt
quizzing-0.0.1.dist-info/METADATA
quizzing-0.0.1.dist-info/WHEEL
quizzing-0.0.1.dist-info/top_level.txt
quizzing-0.0.1.dist-info/RECORD
