Metadata-Version: 2.1
Name: quizzing
Version: 0.0.1
Summary: The quizzing Package is about creating, managing, and conducting interactive quizzes for users, divided into two sub-packages: question_bank and doquiz.
Author-email: "Huan He, Qijia Zheng" <huanhe@student.ubc.ca>
Project-URL: Homepage, https://github.com/Raccoon-he/quizzing-step3
Project-URL: Issues, https://github.com/Raccoon-he/quizzing-step3/issues
Classifier: Programming Language :: Python :: 3
Classifier: License :: OSI Approved :: MIT License
Classifier: Operating System :: OS Independent
Requires-Python: >=3.9
License-File: LICENSE.txt
